ImplicitContextLibrary/ImplicitContextKeywords.resource
ImplicitContextLibrary/__init__.py
tasks.py
robotframework_implicitcontext-0.1.1.dist-info/LICENSE
robotframework_implicitcontext-0.1.1.dist-info/METADATA
robotframework_implicitcontext-0.1.1.dist-info/WHEEL
robotframework_implicitcontext-0.1.1.dist-info/RECORD
